pycdstar/__init__.py
pycdstar/__main__.py
pycdstar/api.py
pycdstar/catalog.py
pycdstar/commands.py
pycdstar/config.py
pycdstar/exception.py
pycdstar/media.py
pycdstar/resource.py
pycdstar-1.1.0.dist-info/LICENSE
pycdstar-1.1.0.dist-info/METADATA
pycdstar-1.1.0.dist-info/WHEEL
pycdstar-1.1.0.dist-info/entry_points.txt
pycdstar-1.1.0.dist-info/top_level.txt
pycdstar-1.1.0.dist-info/RECORD
